rtree/__init__.py
rtree/core.py
rtree/exceptions.py
rtree/finder.py
rtree/index.py
rtree/py.typed
rtree/include/spatialindex/Ball.h
rtree/include/spatialindex/LineSegment.h
rtree/include/spatialindex/MVRTree.h
rtree/include/spatialindex/MovingPoint.h
rtree/include/spatialindex/MovingRegion.h
rtree/include/spatialindex/Point.h
rtree/include/spatialindex/RTree.h
rtree/include/spatialindex/Region.h
rtree/include/spatialindex/SpatialIndex.h
rtree/include/spatialindex/TPRTree.h
rtree/include/spatialindex/TimePoint.h
rtree/include/spatialindex/TimeRegion.h
rtree/include/spatialindex/Version.h
rtree/include/spatialindex/capi/BoundsQuery.h
rtree/include/spatialindex/capi/CountVisitor.h
rtree/include/spatialindex/capi/CustomStorage.h
rtree/include/spatialindex/capi/DataStream.h
rtree/include/spatialindex/capi/Error.h
rtree/include/spatialindex/capi/IdVisitor.h
rtree/include/spatialindex/capi/Index.h
rtree/include/spatialindex/capi/LeafQuery.h
rtree/include/spatialindex/capi/ObjVisitor.h
rtree/include/spatialindex/capi/Utility.h
rtree/include/spatialindex/capi/sidx_api.h
rtree/include/spatialindex/capi/sidx_config.h
rtree/include/spatialindex/capi/sidx_export.h
rtree/include/spatialindex/capi/sidx_impl.h
rtree/include/spatialindex/tools/PointerPool.h
rtree/include/spatialindex/tools/PoolPointer.h
rtree/include/spatialindex/tools/Tools.h
rtree/include/spatialindex/tools/rand48.h
rtree/lib/libspatialindex.dylib
rtree/lib/libspatialindex_c.dylib
Rtree-1.3.0.dist-info/LICENSE.txt
Rtree-1.3.0.dist-info/METADATA
Rtree-1.3.0.dist-info/WHEEL
Rtree-1.3.0.dist-info/top_level.txt
Rtree-1.3.0.dist-info/RECORD
