Metadata-Version: 2.1
Name: Rtree
Version: 1.3.0
Summary: R-Tree spatial index for Python GIS
Author-email: Sean Gillies <sean.gillies@gmail.com>
Maintainer-email: Howard Butler <howard@hobu.co>, Mike Taves <mwtoews@gmail.com>
License: MIT
Project-URL: Documentation, https://rtree.readthedocs.io
Project-URL: Repository, https://github.com/Toblerity/rtree
Keywords: gis,spatial,index,r-tree
Classifier: Development Status :: 5 - Production/Stable
Classifier: Intended Audience :: Developers
Classifier: Intended Audience :: Science/Research
Classifier: License :: OSI Approved :: MIT License
Classifier: Operating System :: OS Independent
Classifier: Programming Language :: Python :: 3
Classifier: Programming Language :: Python :: 3.8
Classifier: Programming Language :: Python :: 3.9
Classifier: Programming Language :: Python :: 3.10
Classifier: Programming Language :: Python :: 3.11
Classifier: Programming Language :: Python :: 3.12
Classifier: Topic :: Scientific/Engineering :: GIS
Classifier: Topic :: Database
Requires-Python: >=3.8
License-File: LICENSE.txt
